ocha_lens/__init__.py
ocha_lens/_version.py
ocha_lens/datasources/ecmwf_storm.py
ocha_lens/datasources/ibtracs.py
ocha_lens/datasources/data/cxml_ecmwf_transformation.xsl
ocha_lens/utils/storm.py
ocha_lens-0.3.2.dist-info/METADATA
ocha_lens-0.3.2.dist-info/WHEEL
ocha_lens-0.3.2.dist-info/licenses/LICENSE
ocha_lens-0.3.2.dist-info/RECORD
